ottoai/__init__.py
ottoai/classes.py
ottoai/helpers.py
ottoai/templates.py
ottoai-0.0.5.dist-info/LICENSE
ottoai-0.0.5.dist-info/METADATA
ottoai-0.0.5.dist-info/WHEEL
ottoai-0.0.5.dist-info/top_level.txt
ottoai-0.0.5.dist-info/RECORD
