Metadata-Version: 2.1
Name: ottoai
Version: 0.0.5
Summary: The most minimalistic library for building intelligent AI Agents straight from Python Objects
Author: MindsDB
Author-email: otto@mindsdb.com
Classifier: Programming Language :: Python :: 3
Classifier: License :: OSI Approved :: MIT License
Classifier: Operating System :: OS Independent
License-File: LICENSE
Requires-Dist: toml
